katalytic/files.py
katalytic_files-0.14.1.dist-info/LICENSE.txt
katalytic_files-0.14.1.dist-info/WHEEL
katalytic_files-0.14.1.dist-info/METADATA
katalytic_files-0.14.1.dist-info/RECORD
