Metadata-Version: 2.1
Name: katalytic-files
Version: 0.14.1
Summary: This plugin adds utilities for working with files to the katalytic namespace
Keywords: automation,filesystem
Author-email: Valentin Neagu <vali19th@protonmail.com>
Requires-Python: >=3.6
Classifier: Development Status :: 3 - Alpha
Classifier: Intended Audience :: Developers
Classifier: Intended Audience :: System Administrators
Classifier: License :: OSI Approved :: MIT License
Classifier: Natural Language :: English
Classifier: Operating System :: OS Independent
Classifier: Programming Language :: Python :: 3
Classifier: Topic :: Software Development :: Libraries
Classifier: Topic :: System :: Filesystems
Classifier: Topic :: System :: Systems Administration
Classifier: Topic :: Utilities
Requires-Dist: katalytic-data>=0.9.1
Requires-Dist: katalytic-pkg>=0.2.0
Requires-Dist: ujson ; extra == "all"
Requires-Dist: pytest ; extra == "dev"
Requires-Dist: pytest-cov ; extra == "dev"
Requires-Dist: pytest-clarity ; extra == "dev"
Requires-Dist: pytest-randomly ; extra == "dev"
Project-URL: homepage, https://gitlab.com/katalytic/katalytic-files.git
Project-URL: repository, https://gitlab.com/katalytic/katalytic-files.git
Provides-Extra: all
Provides-Extra: dev
